ruia/__init__.py
ruia/exceptions.py
ruia/field.py
ruia/item.py
ruia/middleware.py
ruia/request.py
ruia/response.py
ruia/spider.py
ruia/spider_hook.py
ruia/utils/__init__.py
ruia/utils/log.py
tests/__init__.py
tests/test_field.py
tests/test_item.py
tests/test_middleware.py
tests/test_request.py
tests/test_response.py
tests/test_spider.py
tests/for_doc/__init__.py
tests/for_doc/apis/__init__.py
tests/for_doc/apis/test_field.py
ruia-0.8.5.dist-info/LICENSE
ruia-0.8.5.dist-info/METADATA
ruia-0.8.5.dist-info/WHEEL
ruia-0.8.5.dist-info/top_level.txt
ruia-0.8.5.dist-info/RECORD
