Metadata-Version: 2.1
Name: ruia
Version: 0.8.5
Summary: Async Python 3.6+ web scraping micro-framework based on asyncio.
Home-page: https://python-ruia.org/
Author: Howie Hu
Author-email: xiaozizayang@gmail.com
License: MIT
Project-URL: Documentation, https://docs.python-ruia.org/
Project-URL: Source, https://github.com/howie6879/ruia
Platform: UNKNOWN
Classifier: Framework :: AsyncIO
Classifier: Intended Audience :: Developers
Classifier: Development Status :: 4 - Beta
Classifier: License :: OSI Approved :: MIT License
Classifier: Operating System :: POSIX :: Linux
Classifier: Operating System :: MacOS :: MacOS X
Classifier: Operating System :: POSIX :: BSD
Classifier: Operating System :: Microsoft :: Windows
Classifier: Programming Language :: Python :: 3.6
Classifier: Programming Language :: Python :: 3.7
Classifier: Programming Language :: Python :: 3.8
Classifier: Programming Language :: Python :: 3.9
Classifier: Programming Language :: Python :: 3.10
Classifier: Topic :: Internet :: WWW/HTTP
Classifier: Topic :: Software Development :: Libraries :: Application Frameworks
Classifier: Topic :: Software Development :: Libraries :: Python Modules
Requires-Python: >=3.6
License-File: LICENSE
Requires-Dist: aiohttp (>=3.5.4)
Requires-Dist: cssselect
Requires-Dist: lxml
Provides-Extra: uvloop
Requires-Dist: uvloop ; extra == 'uvloop'
